FXrays/__init__.py
FXrays/test.py
FXrays/FXraysmodule.cpython-312-darwin.so
FXrays/_test.py
FXrays/cython_src/FXraysmodule.c
FXrays/cython_src/FXraysmodule.pyx
FXrays-1.3.6.dist-info/RECORD
FXrays-1.3.6.dist-info/WHEEL
FXrays-1.3.6.dist-info/top_level.txt
FXrays-1.3.6.dist-info/METADATA
