Metadata-Version: 2.1
Name: FXrays
Version: 1.3.6
Summary: Computes extremal rays with filtering
Author-email: Marc Culler <culler@marc-culler.info>, "Nathan M. Dunfield" <nathan@dunfield.info>
License: GPLv2+
Project-URL: Homepage, https://github.com/3-manifolds/FXrays
Classifier: Development Status :: 5 - Production/Stable
Classifier: Intended Audience :: Science/Research
Classifier: License :: OSI Approved :: GNU General Public License v2 or later (GPLv2+)
Classifier: Operating System :: OS Independent
Classifier: Programming Language :: C
Classifier: Programming Language :: Cython
Classifier: Programming Language :: Python
Classifier: Topic :: Scientific/Engineering :: Mathematics
Requires-Python: >=3.7
